{
  "$schema": "https://static.modelcontextprotocol.io/schemas/2025-12-11/server.schema.json",
  "name": "io.github.do-droid/seoul-essentials",
  "description": "22,000+ Seoul public facility data for tourists: restrooms, pharmacies, WiFi, AEDs, and subway.",
  "repository": {
    "url": "https://github.com/do-droid/seoul-essentials",
    "source": "github"
  },
  "version": "0.2.0",
  "packages": [
    {
      "registryType": "oci",
      "identifier": "ghcr.io/do-droid/seoul-essentials:0.2.0",
      "transport": {
        "type": "streamable-http",
        "url": "https://seoul-essentials-mcp-230987091625.asia-northeast3.run.app/mcp"
      }
    }
  ],
  "tools": [
    {
      "name": "find_places",
      "description": "Search for public facilities in Seoul by type and conditions"
    },
    {
      "name": "get_place_detail",
      "description": "Get full details of a specific place by its ID"
    },
    {
      "name": "find_nearby",
      "description": "Find facilities near GPS coordinates, sorted by distance"
    },
    {
      "name": "get_subway_timetable",
      "description": "Get Seoul subway timetable for a specific station"
    }
  ]
}
